CHANGES.txt
DEVELOP.txt
LICENSE.txt
buildout.cfg
setup.py
bootstrap/bootstrap.py
src/zc/__init__.py
src/zc.blist.egg-info/PKG-INFO
src/zc.blist.egg-info/SOURCES.txt
src/zc.blist.egg-info/dependency_links.txt
src/zc.blist.egg-info/not-zip-safe
src/zc.blist.egg-info/requires.txt
src/zc.blist.egg-info/top_level.txt
src/zc/blist/CHANGES.txt
src/zc/blist/README.txt
src/zc/blist/TODO.txt
src/zc/blist/__init__.py
src/zc/blist/regression.txt
src/zc/blist/testing.py
src/zc/blist/tests.py