Metadata-Version: 1.0
Name: zc.blist
Version: 1.0b2
Summary: ZODB-friendly BTree-based list implementation
Home-page: UNKNOWN
Author: Gary Poster
Author-email: gary.poster@canonical.com
License: ZPL
Platform: UNKNOWN
